queuehealth/__init__.py
queuehealth/apps.py
queuehealth/management/__init__.py
queuehealth/management/commands/__init__.py
queuehealth/management/commands/test_queue_health.py
queuehealth/management/commands/update_queue_timestamp.py
django_queue_health-0.2.1.dist-info/AUTHORS.md
django_queue_health-0.2.1.dist-info/LICENSE
django_queue_health-0.2.1.dist-info/METADATA
django_queue_health-0.2.1.dist-info/WHEEL
django_queue_health-0.2.1.dist-info/top_level.txt
django_queue_health-0.2.1.dist-info/RECORD
