Metadata-Version: 2.1
Name: django-queue-health
Version: 0.2.1
Summary: Queue health checker for Django
Home-page: https://gitlab.com/adaptiware/django-queue-health
Author: Artem Markovskyi
Author-email: artem@adaptiware.com
Classifier: Environment :: Web Environment
Classifier: Operating System :: OS Independent
Classifier: License :: OSI Approved :: MIT License
Classifier: Programming Language :: Python :: 2
Classifier: Framework :: Django
Requires-Python: >=2.7
License-File: LICENSE
License-File: AUTHORS.md
